SentimentAnalysisDarijaNZ/__init__.py
SentimentAnalysisDarijaNZ/filtering.py
SentimentAnalysisDarijaNZ/sentiment.py
SentimentAnalysisDarijaNZ/similarity.py
SentimentAnalysisDarijaNZ/utils.py
SentimentAnalysisDarijaNZ-0.3.2.dist-info/LICENSE
SentimentAnalysisDarijaNZ-0.3.2.dist-info/METADATA
SentimentAnalysisDarijaNZ-0.3.2.dist-info/WHEEL
SentimentAnalysisDarijaNZ-0.3.2.dist-info/top_level.txt
SentimentAnalysisDarijaNZ-0.3.2.dist-info/RECORD
