Metadata-Version: 2.2
Name: SentimentAnalysisDarijaNZ
Version: 0.3.2
Summary: C'est une bibliothèque Python modulaire qui fournit des outils pour le calcul de similarité, le filtrage de données, et l'analyse de sentiments.
Home-page: https://github.com/Benhamdane/SentimentAnalysisDarijaNZ
Author: Nawfal BENHAMDANE
Author-email: benhamdane2003@gmail.com
Classifier: Programming Language :: Python :: 3
Classifier: License :: OSI Approved :: MIT License
Classifier: Operating System :: OS Independent
Requires-Python: >=3.6
License-File: LICENSE
Dynamic: author
Dynamic: author-email
Dynamic: classifier
Dynamic: description
Dynamic: description-content-type
Dynamic: home-page
Dynamic: requires-python
Dynamic: summary
